mortar_sqlalchemy/__init__.py
mortar_sqlalchemy/testing.py
mortar_sqlalchemy/mixins/__init__.py
mortar_sqlalchemy/mixins/common.py
mortar_sqlalchemy/mixins/temporal.py
mortar_sqlalchemy-4.0.0.dist-info/LICENSE.txt
mortar_sqlalchemy-4.0.0.dist-info/METADATA
mortar_sqlalchemy-4.0.0.dist-info/WHEEL
mortar_sqlalchemy-4.0.0.dist-info/top_level.txt
mortar_sqlalchemy-4.0.0.dist-info/RECORD
